geepillow/__init__.py
geepillow/blocks.py
geepillow/colors.py
geepillow/eeblocks.py
geepillow/grids.py
geepillow/image.py
geepillow/py.typed
geepillow/strips.py
geepillow/fonts/OpenSans-Bold.ttf
geepillow/fonts/OpenSans-BoldItalic.ttf
geepillow/fonts/OpenSans-Italic.ttf
geepillow/fonts/OpenSans-Light.ttf
geepillow/fonts/OpenSans-Regular.ttf
geepillow/fonts/__init__.py
geepillow-1.1.2.dist-info/METADATA
geepillow-1.1.2.dist-info/WHEEL
geepillow-1.1.2.dist-info/licenses/AUTHORS.rst
geepillow-1.1.2.dist-info/licenses/LICENSE
geepillow-1.1.2.dist-info/RECORD
