Metadata-Version: 2.4
Name: geepillow
Version: 1.1.2
Summary: Download Satellite images from GEE as Pillow images and create image strips and grids
Project-URL: Homepage, https://github.com/fitoprincipe/geepillow
Author-email: Rodrigo Esteban Principe <fitoprincipe82@gmail.com>
License: MIT
License-File: AUTHORS.rst
License-File: LICENSE
Keywords: Python,skeleton
Classifier: Development Status :: 3 - Alpha
Classifier: Intended Audience :: Developers
Classifier: License :: OSI Approved :: MIT License
Classifier: Programming Language :: Python :: 3.10
Classifier: Programming Language :: Python :: 3.11
Requires-Python: >=3.10
Requires-Dist: deprecated>=1.2.14
Requires-Dist: earthengine-api
Requires-Dist: geetools
Requires-Dist: pillow
Requires-Dist: requests
Provides-Extra: doc
Requires-Dist: pydata-sphinx-theme; extra == 'doc'
Requires-Dist: sphinx-autoapi; extra == 'doc'
Requires-Dist: sphinx-copybutton; extra == 'doc'
Requires-Dist: sphinx-design; extra == 'doc'
Requires-Dist: sphinx>=6.2.1; extra == 'doc'
Provides-Extra: test
Requires-Dist: pytest; extra == 'test'
Requires-Dist: pytest-cov; extra == 'test'
Requires-Dist: pytest-deadfixtures; extra == 'test'
Requires-Dist: pytest-gee; extra == 'test'
Requires-Dist: pytest-regressions; extra == 'test'
